MANIFEST.in
README.md
setup.cfg
setup.py
human_time.egg-info/PKG-INFO
human_time.egg-info/SOURCES.txt
human_time.egg-info/dependency_links.txt
human_time.egg-info/entry_points.txt
human_time.egg-info/requires.txt
human_time.egg-info/top_level.txt
src/__init__.py
src/app.py
src/cli_client.py
src/clock.py
src/humantime.yaml
src/request_handler.py
test/__init__.py
test/fixtures.py
test/test_api.py
test/test_cli.py