Metadata-Version: 2.1
Name: human-time
Version: 1.0.6
Summary: Converts digit based time formats to the english language equivalent
Home-page: https://github.com/Jonnyneill/human-time
Author: Jonathan Neill
Author-email: jonnyneill@hotmail.com
License: MIT
Keywords: talking clock human time
Platform: UNKNOWN
Classifier: Development Status :: 3 - Alpha
Classifier: Intended Audience :: Developers
Classifier: Topic :: Software Development :: Build Tools
Classifier: License :: OSI Approved :: MIT License
Classifier: Programming Language :: Python :: 3.6
Classifier: Programming Language :: Python :: 3.7
Classifier: Operating System :: OS Independent
Requires-Python: >=3.6
